rdadccvt/__init__.py
rdadccvt/balzer.py
rdadccvt/balzerio.py
rdadccvt/helpers.py
rdadccvt/union_find.py
rdadccvt-1.6.0.dist-info/LICENSE
rdadccvt-1.6.0.dist-info/METADATA
rdadccvt-1.6.0.dist-info/WHEEL
rdadccvt-1.6.0.dist-info/top_level.txt
rdadccvt-1.6.0.dist-info/RECORD
