Metadata-Version: 2.1
Name: rdadccvt
Version: 1.6.0
Summary: Balzer's algorithm (DCCVT) to find a maximally population compact map
Home-page: https://github.com/rdatools/rdadccvt
Author: alecramsay
Author-email: Alec Ramsay <a73cram5ay@gmail.com>
License: MIT
Project-URL: Homepage, https://github.com/rdatools/rdadccvt
Project-URL: Bug Tracker, https://github.com/rdatools/rdabase/issues
Classifier: Programming Language :: Python :: 3
Classifier: License :: OSI Approved :: MIT License
Classifier: Operating System :: OS Independent
Requires-Python: >=3.10
License-File: LICENSE
Requires-Dist: rdabase
Requires-Dist: scipy
